[{"id":0,"username":"GilbertP","password":"$2b$10$ytulIaJ/4uCch2DEr2l.euQqO91Oqfc9i/HY11Xb9JKu3nsi1KN92"},{"id":1,"username":"GilbertP","password":"$2b$10$PSRPOL7eCEpXS.og3N0/kuq.7ZIvyuRj3K9FGYwgIo6ulqhoBpKqS"},{"id":2,"username":"GilbertP","password":"$2b$10$QrAu5MhBf.QYDJLqj0CC0.pI7TuF3fvC8ao5K3rmvTrntbVCSEauu"},{"id":3,"username":"GilbertP","password":"$2b$10$Lu2OsmnXfzailspBlPP2LOElFv51W9qTkzRtLxhDrlDEjcVyIN0fC"},{"id":4,"username":"GilbertP","password":"$2b$10$8LqGVLPFnYggfEifsA5Dz.y6F9aMenaUw3tBnOj1BYZAK6QIbfsgK"},{"id":5,"username":"GilbertP","password":"$2b$10$rXDSeQetrYv1Ecu8Ri.WIu6nDnJN88e2nBa.ccVYEBVaY.xcUksZC"},{"id":6,"username":"GilbertP","password":"$2b$10$hEOUDTVVriTdwltUB3RVqOCC9q3hCP01T/JJjmd7EV7D23VPuCngK"}]